ovos_stt_plugin_selene/__init__.py
ovos_stt_plugin_selene/version.py
ovos_stt_plugin_selene-0.0.3.dist-info/METADATA
ovos_stt_plugin_selene-0.0.3.dist-info/WHEEL
ovos_stt_plugin_selene-0.0.3.dist-info/entry_points.txt
ovos_stt_plugin_selene-0.0.3.dist-info/top_level.txt
ovos_stt_plugin_selene-0.0.3.dist-info/zip-safe
ovos_stt_plugin_selene-0.0.3.dist-info/RECORD
