Metadata-Version: 2.1
Name: ovos-stt-plugin-selene
Version: 0.0.3
Summary: A stt plugin for mycroft using the mycroft selene backend services
Home-page: https://github.com/OpenVoiceOS/ovos-stt-plugin-selene
Author: JarbasAi
Author-email: jarbasai@mailfence.com
License: Apache-2.0
Keywords: mycroft ovos plugin stt
Platform: UNKNOWN
Classifier: Development Status :: 3 - Alpha
Classifier: Intended Audience :: Developers
Classifier: Topic :: Text Processing :: Linguistic
Classifier: License :: OSI Approved :: Apache Software License
Classifier: Programming Language :: Python :: 2
Classifier: Programming Language :: Python :: 2.7
Classifier: Programming Language :: Python :: 3
Classifier: Programming Language :: Python :: 3.0
Classifier: Programming Language :: Python :: 3.1
Classifier: Programming Language :: Python :: 3.2
Classifier: Programming Language :: Python :: 3.3
Classifier: Programming Language :: Python :: 3.4
Classifier: Programming Language :: Python :: 3.5
Classifier: Programming Language :: Python :: 3.6
Requires-Dist: requests
Requires-Dist: ovos-utils (~=0.0.8)
Requires-Dist: ovos-plugin-manager (~=0.0.1)
Requires-Dist: ovos-backend-client (~=0.0.6)
